alpha_shifter_cypher/__init__.py
alpha_shifter_cypher/main.py
alpha_shifter_cypher-0.2.0.dist-info/entry_points.txt
alpha_shifter_cypher-0.2.0.dist-info/LICENSE
alpha_shifter_cypher-0.2.0.dist-info/WHEEL
alpha_shifter_cypher-0.2.0.dist-info/METADATA
alpha_shifter_cypher-0.2.0.dist-info/RECORD
