Metadata-Version: 2.1
Name: alpha-shifter-cypher
Version: 0.2.0
Summary: An example Python CLI program distributed via PyPI.
Author: Benjamin Rosen
Author-email: ben@classy.name
Requires-Python: >=3.6,<4.0
Classifier: Programming Language :: Python :: 3
Classifier: Programming Language :: Python :: 3.6
Classifier: Programming Language :: Python :: 3.7
Classifier: Programming Language :: Python :: 3.8
Requires-Dist: fire (>=0.3.1,<0.4.0)
